<?xml version="1.0" encoding="utf-8"?>
  <Thrall available="47479" attributeid="Thra" franchise="Warcraft" type="Melee" difficulty="Easy"
          portrait="storm_ui_ingame_heroselect_btn_thrall.png" loading="storm_ui_ingame_hero_loadingscreen_thrall.png" leader="storm_ui_ingame_hero_leaderboard_thrall.png">
    <Roles>Assassin</Roles>
    <Abilities>
    </Abilities>
    <Talents>
      <Level1>
        <ThrallEchooftheElements name="Echo of the Elements" desc="ThrallEchooftheElements">storm_ui_icon_thrall_chainlightning.png</ThrallEchooftheElements>
        <ThrallCrashLightning name="Crash Lightning" desc="ThrallCrashLightning">storm_ui_icon_thrall_chainlightning_var1.png</ThrallCrashLightning>
        <ThrallMasteryRollingThunder name="Mastery Rolling Thunder" desc="ThrallRollingThunderTalent">storm_ui_icon_thrall_chainlightning_var2.png</ThrallMasteryRollingThunder>
      </Level1>
      <Level4>
        <ThrallFeralResilience name="Feral Resilience" desc="ThrallFeralResilience">storm_ui_icon_thrall_feralspirit.png</ThrallFeralResilience>
        <ThrallFrostwolfPack name="Frostwolf Pack" desc="ThrallFrostwolfPack">storm_ui_icon_thrall_feralspirit_var1.png</ThrallFrostwolfPack>
        <ThrallMasteryManaTide name="Mana Tide" desc="ThrallManaTideTalent">storm_ui_icon_thrall_frostwolfresilience.png</ThrallMasteryManaTide>
      </Level4>
      <Level7>
        <ThrallMaelstromWeapon name="Maelstrom Weapon" desc="ThrallMaelstromWeapon">storm_ui_icon_thrall_windfury_var1.png</ThrallMaelstromWeapon>
        <ThrallAncestralWrath name="Ancestral Wrath" generic="true" desc="ThrallAncestralWrath">storm_ui_icon_talent_bloodforblood.png</ThrallAncestralWrath>
        <GenericTalentFollowThrough name="Follow Through" desc="GenericFollowThroughTalent">storm_ui_icon_talent_autoattack_damage.png</GenericTalentFollowThrough>
      </Level7>
      <Level10>
        <ThrallHeroicAbilitySundering name="Sundering" desc="Sundering">storm_ui_icon_thrall_sundering.png</ThrallHeroicAbilitySundering>
        <ThrallHeroicAbilityEarthquake name="Earthquake" desc="ThrallEarthquake">storm_ui_icon_thrall_earthquake.png</ThrallHeroicAbilityEarthquake>
      </Level10>
      <Level13>
        <ThrallMasteryGraceOfAir name="Grace Of Air" desc="ThrallGraceOfAirTalent">storm_ui_icon_thrall_windfury.png</ThrallMasteryGraceOfAir>
        <ThrallMasteryFrostwolfsGrace name="Frostwolf's Grace" desc="ThrallFrostwolfResilienceSurgeOfHealing">storm_ui_icon_thrall_frostwolfresilience.png</ThrallMasteryFrostwolfsGrace>
        <ThrallSpiritShield name="Spirit Shield" generic="true" desc="ThrallSpiritShield">storm_ui_icon_talent_spellshield.png</ThrallSpiritShield>
      </Level13>
      <Level16>
        <ThrallMasteryTempestFury name="Tempest Fury" desc="ThrallTempestFuryTalent">storm_ui_icon_thrall_windfury.png</ThrallMasteryTempestFury>
        <ThrallThunderstorm name="Thunderstorm" desc="ThrallThunderstorm">storm_ui_icon_thrall_chainlightning.png</ThrallThunderstorm>
        <ThrallAlphaWolf name="Alpha Wolf" desc="ThrallAlphaWolf">storm_ui_icon_thrall_feralspirit.png</ThrallAlphaWolf>
      </Level16>
      <Level20>
        <ThrallMasteryWorldbreaker name="World breaker" desc="ThrallWorldbreakerTalent">storm_ui_icon_thrall_sundering.png</ThrallMasteryWorldbreaker>
        <ThrallMasteryEarthenShields name="Earthen Shields" desc="ThrallEarthenShieldsTalent">storm_ui_icon_thrall_earthquake.png</ThrallMasteryEarthenShields>
        <GenericTalentNexusBlades name="Nexus Blades" desc="NexusBladesTalent">storm_ui_icon_talent_autoattack_slow.png</GenericTalentNexusBlades>
        <ThrallWindRush name="Wind Rush" generic="true" desc="ThrallWindRush">storm_ui_icon_talent_boltofthestorm.png</ThrallWindRush>
      </Level20>
  </Talents>
</Thrall>
