<?xml version="1.0" encoding="utf-8"?>
<Chen available="47479" attributeid="Chen" franchise="Warcraft" type="Melee" difficulty="Hard">
  <Portrait>storm_ui_ingame_heroselect_btn_chen.png</Portrait>
  <Loading>storm_ui_ingame_hero_loadingscreen_chen.png</Loading>
  <Leader>storm_ui_ingame_hero_leaderboard_chen.png</Leader>
  <Roles>Warrior</Roles>
  <Abilities>
  </Abilities>
  <Talents>
    <Level1>
      <ChenAccumulatingFlame name="Accumulating Flame" desc="ChenAccumulatingFlame">
        <Icon>storm_ui_icon_chen_breathoffire.png</Icon>
      </ChenAccumulatingFlame>
      <ChenGroundingBrew name="Grounding Brew" desc="ChenFortifyingBrewGroundingBrewTalent">
        <Icon>storm_ui_icon_chen_fortifyingbrew_a.png</Icon>
      </ChenGroundingBrew>
      <ChenFreshestIngredients name="Freshest Ingredients" desc="ChenFreshestIngredients">
        <Icon>storm_ui_icon_chen_fortifyingbrew.png</Icon>
      </ChenFreshestIngredients>
      <ChenElusiveBrawler name="Elusive Brawler" desc="ChenElusiveBrawler">
        <Icon>storm_ui_icon_chen_elusivebrew.png</Icon>
      </ChenElusiveBrawler>
    </Level1>
    <Level4>
      <ChenDeadlyStrike name="Deadly Strike" desc="ChenFlyingKickDeadlyStrikeTalent">
        <Icon>storm_ui_icon_chen_flyingkick.png</Icon>
      </ChenDeadlyStrike>
      <ChenKegToss name="Keg Toss" desc="ChenKegSmashKegTossTalent">
        <Icon>storm_ui_icon_chen_kegsmash.png</Icon>
      </ChenKegToss>
      <ChenRingofFire name="Ring of Fire" desc="ChenBreathOfFireRingOfFireTalent">
        <Icon>storm_ui_icon_chen_breathoffire.png</Icon>
      </ChenRingofFire>
    </Level4>
    <Level7>
      <ChenBrewmastersBalance name="Brewmaster's Balance" desc="ChenFortifyingBrewBrewmastersBalanceTalent">
        <Icon>storm_ui_icon_chen_fortifyingbrew.png</Icon>
      </ChenBrewmastersBalance>
      <ChenBolderFlavor name="Bolder Flavor" desc="ChenFortifyingBrewBolderFlavorTalent">
        <Icon>storm_ui_icon_chen_fortifyingbrew_a.png</Icon>
      </ChenBolderFlavor>
      <ChenRefreshingElixir name="Refreshing Elixir" desc="ChenRefreshingElixir">
        <Icon generic="true">storm_ui_icon_talent_amplifiedhealing.png</Icon>
      </ChenRefreshingElixir>
    </Level7>
    <Level10>
      <ChenHeroicAbilityWanderingKeg name="Wandering Keg" desc="ChenWanderingKeg">
        <Icon>storm_ui_icon_chen_wanderingkeg.png</Icon>
      </ChenHeroicAbilityWanderingKeg>
      <ChenHeroicAbilityStormEarthFire name="Storm, Earth, Fire" desc="ChenStormEarthFire">
        <Icon>storm_ui_icon_chen_stormearthfire.png</Icon>
      </ChenHeroicAbilityStormEarthFire>
    </Level10>
    <Level13>
      <ChenPressurePoint name="Pressure Point" desc="ChenFlyingKickPressurePointTalent">
        <Icon>storm_ui_icon_chen_flyingkick.png</Icon>
      </ChenPressurePoint>
      <ChenMasteryKegSmashATouchOfHoney name="A Touch of Honey" desc="ChenKegSmashATouchOfHoneyTalent">
        <Icon>storm_ui_icon_chen_kegsmash.png</Icon>
      </ChenMasteryKegSmashATouchOfHoney>
      <ChenWitheringFlames name="Withering Flames" desc="ChenWitheringFlames">
        <Icon>storm_ui_icon_chen_breathoffire.png</Icon>
      </ChenWitheringFlames>
    </Level13>
    <Level16>
      <ChenFlyingLeap name="Flying Leap" desc="ChenFlyingLeap">
        <Icon>storm_ui_icon_chen_flyingkick.png</Icon>
      </ChenFlyingLeap>
      <ChenAnotherRound name="Another Round" desc="ChenAnotherRound">
        <Icon>storm_ui_icon_chen_kegsmash.png</Icon>
      </ChenAnotherRound>
      <ChenMasteryFortifyingBrewEnoughToShare name="Enough to Share" desc="ChenFortifyingBrewEnoughToShareTalent">
        <Icon>storm_ui_icon_chen_fortifyingbrew.png</Icon>
      </ChenMasteryFortifyingBrewEnoughToShare>
    </Level16>
    <Level20>
      <ChenMasteryWanderingKegUntappedPotential name="Untapped Potential" desc="ChenWanderingKegUntappedPotentialTalent">
        <Icon>storm_ui_icon_chen_wanderingkeg.png</Icon>
      </ChenMasteryWanderingKegUntappedPotential>
      <ChenElementalConduit name="Elemental Conduit" desc="ChenStormEarthFireElementalConduitTalent">
        <Icon>storm_ui_icon_chen_stormearthfire.png</Icon>
      </ChenElementalConduit>
      <ChenPurifyingBrew name="Purifying Brew" desc="ChenPurifyingBrew">
        <Icon>storm_ui_icon_chen_fortifyingbrew_a.png</Icon>
      </ChenPurifyingBrew>
      <ChenStormstoutSecretRecipe name="Stormstout Secret Recipe" desc="ChenStormstoutSecretRecipe">
        <Icon>storm_ui_icon_chen_stormstoutsecretrecipe.png</Icon>
      </ChenStormstoutSecretRecipe>
    </Level20>
    <Old>
      <GenericTalentRegenerationMaster name="Regeneration Master">storm_ui_icon_talent_regenerationmaster.png</GenericTalentRegenerationMaster>
      <ChenMasteryKegSmashKegToss name="Keg Toss">storm_ui_icon_chen_kegsmash.png</ChenMasteryKegSmashKegToss>
      <ChenMasteryFortifyingBrewGroundingBrew name="Grounding Brew">storm_ui_icon_chen_fortifyingbrew.png</ChenMasteryFortifyingBrewGroundingBrew>
      <ChenMasteryBreathOfFireConsumingFlame name="Consuming Flame">storm_ui_icon_chen_breathoffire.png</ChenMasteryBreathOfFireConsumingFlame>
      <ChenTalentSwiftReflexes name="Swift Reflexes">storm_ui_icon_Chen_SwiftReflexes.png</ChenTalentSwiftReflexes>
      <ChenMasteryFlyingKickDeadlyStrike name="Deadly Strike">storm_ui_icon_chen_flyingkick.png</ChenMasteryFlyingKickDeadlyStrike>
      <GenericTalentAmplifiedHealing name="Amplified Healing">storm_ui_icon_talent_amplifiedhealing.png</GenericTalentAmplifiedHealing>
      <ChenMasteryBreathOfFireDeepBreath name="Deep Breath">storm_ui_icon_chen_breathoffire.png</ChenMasteryBreathOfFireDeepBreath>
      <ChenMasteryKegSmashFullKeg name="Full Keg">storm_ui_icon_chen_kegsmash.png</ChenMasteryKegSmashFullKeg>
      <ChenMasteryFortifyingBrewCombatStance name="Combat Stance">storm_ui_icon_chen_fortifyingbrew.png</ChenMasteryFortifyingBrewCombatStance>
      <ChenMasteryBrewmastersBalance name="Brewmaster's Balance">storm_ui_icon_chen_fortifyingbrew_a.png</ChenMasteryBrewmastersBalance>
      <ChenMasteryBreathOfFireRingOfFire name="Ring of Fire">storm_ui_icon_chen_breathoffire.png</ChenMasteryBreathOfFireRingOfFire>
      <ChenMasteryFlyingKickBrewStrike name="Brew Strike">storm_ui_icon_chen_flyingkick.png</ChenMasteryFlyingKickBrewStrike>
      <GenericTalentRelentless name="Relentless">storm_ui_icon_Talent_Relentless.png</GenericTalentRelentless>
      <ChenCombatStyleBottomlessMug name="Bottomless Mug">storm_ui_icon_chen_fortifyingbrew.png</ChenCombatStyleBottomlessMug>
      <ChenMasteryFortifyingBrewBolderFlavor name="Bolder Flavor">storm_ui_icon_chen_fortifyingbrew_a.png</ChenMasteryFortifyingBrewBolderFlavor>
      <ChenMasteryFlyingKickPressurePoint name="Pressure Point">storm_ui_icon_chen_flyingkick.png</ChenMasteryFlyingKickPressurePoint>
      <ChenMasteryFlyingKickCombinationAttack name="Combination Attack">storm_ui_icon_chen_flyingkick_a.png</ChenMasteryFlyingKickCombinationAttack>
      <ChenMasteryStormEarthFireElementalConduit name="Elemental Conduit">storm_ui_icon_chen_stormearthfire.png</ChenMasteryStormEarthFireElementalConduit>
      <GenericTalentHardenedShield name="Hardened Shield">storm_ui_icon_Talent_HardenedShield.png</GenericTalentHardenedShield>
      <GenericTalentFlashoftheStorms name="Bolt of the Storm">storm_ui_icon_talent_boltofthestorm.png</GenericTalentFlashoftheStorms>
    </Old>
  </Talents>
</Chen>